computer_use_modal/__init__.py
computer_use_modal/app.py
computer_use_modal/demo.py
computer_use_modal/streamlit.py
computer_use_modal/sandbox/__init__.py
computer_use_modal/sandbox/bash_manager.py
computer_use_modal/sandbox/edit_manager.py
computer_use_modal/sandbox/io.py
computer_use_modal/sandbox/sandbox_manager.py
computer_use_modal/server/__init__.py
computer_use_modal/server/messages.py
computer_use_modal/server/prompts.py
computer_use_modal/server/server.py
computer_use_modal/tools/__init__.py
computer_use_modal/tools/base.py
computer_use_modal/tools/bash.py
computer_use_modal/tools/computer/__init__.py
computer_use_modal/tools/computer/computer.py
computer_use_modal/tools/computer/types.py
computer_use_modal/tools/edit/__init__.py
computer_use_modal/tools/edit/edit.py
computer_use_modal/tools/edit/types.py
computer_use_modal/vnd/__init__.py
computer_use_modal/vnd/anthropic/__init__.py
computer_use_modal/vnd/anthropic/tools/__init__.py
computer_use_modal/vnd/anthropic/tools/computer.py
computer_use_modal/vnd/anthropic/tools/edit.py
computer_use_modal/vnd/anthropic/tools/shared.py
computer_use_modal-0.1.2.dist-info/METADATA
computer_use_modal-0.1.2.dist-info/WHEEL
computer_use_modal-0.1.2.dist-info/top_level.txt
computer_use_modal-0.1.2.dist-info/RECORD
