Metadata-Version: 2.1
Name: computer-use-modal
Version: 0.1.2
Summary: Anthropic Computer Use with Modal Sandboxes
Project-URL: Homepage, https://musings.yasyf.com/improving-claude-computer-use/
Project-URL: Repository, https://github.com/yasyf/anthropic-tool-use-modal.git
Requires-Python: >=3.12
Requires-Dist: annotated-types >=0.7.0
Requires-Dist: anthropic >=0.37.1
Requires-Dist: backoff >=2.2.1
Requires-Dist: fuzzysearch >=0.7.3
Requires-Dist: modal >=0.64.211
Requires-Dist: pydantic >=2.9.2
Requires-Dist: rich >=13.9.3
Requires-Dist: uuid6 >=2024.7.10
Requires-Dist: wand >=0.6.13
